pyasge.cp38-win32.pyd
pyasge-2.0.0.dist-info/LICENSE
pyasge-2.0.0.dist-info/METADATA
pyasge-2.0.0.dist-info/WHEEL
pyasge-2.0.0.dist-info/top_level.txt
pyasge-2.0.0.dist-info/RECORD
