Metadata-Version: 2.1
Name: pyasge
Version: 2.0.0
Summary: Python bindings for ASGE
Home-page: https://github.com/HuxyUK/pyasge
Author: James Huxtable
Author-email: HuxyUK@users.noreply.github.com
License: MIT
Project-URL: Documentation, https://huxyuk.github.io/pyasge
Project-URL: Source, https://github.com/HuxyUK/pyasge
Project-URL: Tracker, https://github.com/HuxyUK/pyasge/issues
Platform: UNKNOWN
Classifier: Development Status :: 5 - Production/Stable
Classifier: Intended Audience :: Developers
Classifier: Intended Audience :: Education
Classifier: Operating System :: Microsoft :: Windows :: Windows 10
Classifier: Operating System :: POSIX :: Linux
Classifier: Operating System :: MacOS
Classifier: License :: OSI Approved :: MIT License
Classifier: Programming Language :: Python :: 3.7
Classifier: Programming Language :: Python :: 3.8
Classifier: Programming Language :: Python :: 3.9
Classifier: Programming Language :: Python :: 3.10
Classifier: Topic :: Games/Entertainment
License-File: LICENSE
Requires-Dist: numpy
